{
  "id": "itemformat",
  "title": [
    {
      "lang": "de",
      "value": "Vokabulare zur Beschreibung des Itemformates"
    }
  ],
  "csv_delimiter": ",",
  "base": "https://w3id.org/iqb/v34",
  "outDir": "dist_ttl",
  "idPattern": "^[abcdefghprqstuvxyz]{1}[2345679]{1}[abcdefghprqstuvxyz]{1}$",
  "creator": "IQB - Institut zur Qualitätsentwicklung im Bildungswesen",
  "vocabularies": [
    {
      "id": "en",
      "title": [
        {
          "lang": "de",
          "value": "Itemformat Englisch Sek I"
        }
      ],
      "filenameSource": "en.csv",
      "filenameTarget": "en.ttl",
      "description": [
        {
          "lang": "de",
          "value": "Itemformat Englisch Sek I and description modified and long text "
        }
      ]
    },
    {
      "id": "3e",
      "title": [
        {
          "lang": "de",
          "value": "Itemformat 3er Liste"
        }
      ],
      "filenameSource": "3e.csv",
      "filenameTarget": "3e.ttl",
      "description": [
        {
          "lang": "de",
          "value": ""
        }
      ]
    },
    {
      "id": "5e",
      "title": [
        {
          "lang": "de",
          "value": "Itemformat 5er Liste"
        }
      ],
      "filenameSource": "5e.csv",
      "filenameTarget": "5e.ttl",
      "description": [
        {
          "lang": "de",
          "value": "Itemformat 5er Liste description"
        }
      ]
    }
  ]
}
